psycopgbinary.py
psycopgbinary-0.0.1.dist-info/LICENSE
psycopgbinary-0.0.1.dist-info/METADATA
psycopgbinary-0.0.1.dist-info/WHEEL
psycopgbinary-0.0.1.dist-info/top_level.txt
psycopgbinary-0.0.1.dist-info/RECORD
